MANIFEST.in
README.md
pytemplate.py
secretary.py
setup.py
tests.py
pytemplateproc.egg-info/PKG-INFO
pytemplateproc.egg-info/SOURCES.txt
pytemplateproc.egg-info/dependency_links.txt
pytemplateproc.egg-info/requires.txt
pytemplateproc.egg-info/top_level.txt