Metadata-Version: 1.0
Name: pytemplateproc
Version: 0.4.2
Summary: Template processor
Home-page: https://github.com/krotos139/pytemplate
Author: Yuri V. Yakovlev
Author-email: krotos139@gmail.com
License: GPL v3
Keywords: jinja2 odt text template
Platform: UNKNOWN
